[
  {
    "Title": "Menu(菜单)",
    "DllName": "",
    "ClassName": "",
    "Children": [
      {
        "Title": "Control(控件)",
        "DllName": "",
        "ClassName": "",
        "Children": [
          {
            "Title": "UserControl(自定义控件)",
            "DllName": "",
            "ClassName": "",
            "Children": [
              {
                "Title": "Creation and use of UserControl(用户控件的创建与使用)",
                "DllName": "",
                "ClassName": "",
                "Children": [
                  {
                    "Title": "UserControl1(用户控件1)",
                    "DllName": "WpfDemo.exe",
                    "ClassName": "WpfDemo.UserControlDemo.OwnUserControl",
                    "Children": [
                    ]
                  },
                  {
                    "Title": "Use UserControl1 in UserControl2(嵌套用户控件1)",
                    "DllName": "WpfDemo.exe",
                    "ClassName": "WpfDemo.UserControlDemo.UseUserControlUserControl",
                    "Children": [
                    ]
                  },
                  {
                    "Title": "Use UserControl1 and UserControl2(嵌套两个用户控件)",
                    "DllName": "WpfDemo.exe",
                    "ClassName": "WpfDemo.UserControlDemo.UseUserControlWindow",
                    "Children": [
                    ]
                  }
                ]
              },
              {
                "Title": "Dynamically generate DataGrid(动态生成DataGrid)",
                "DllName": "WpfDemo.exe",
                "ClassName": "WpfDemo.DynamicallyGeneratedDataGrid.DemoWindow",
                "Children": [
                ]
              },
              {
                "Title": "Input that Only Allows Numbers(只允许输入数字的输入框)",
                "DllName": "WpfDemo.exe",
                "ClassName": "WpfDemo.InputOnlyNumber.InputOnlyNumberWindow",
                "Children": [
                ]
              },
              {
                "Title": "Numeric Keypad(9格数字键盘)",
                "DllName": "WpfDemo.exe",
                "ClassName": "WpfDemo.InputNumberWindow",
                "Children": [
                ]
              },
              {
                "Title": "UserControl that can be dragged and zoomed(可拖拽缩放控件)",
                "DllName": "",
                "ClassName": "",
                "Children": [
                  {
                    "Title": "UserControl1",
                    "DllName": "WpfDemo.exe",
                    "ClassName": "WpfDemo.MoveAndResizeControl.MoveAndResizeControlWindow",
                    "Children": [
                    ]
                  },
                  {
                    "Title": "UserControl2",
                    "DllName": "WpfDemo.exe",
                    "ClassName": "WpfDemo.MoveAndResizeControl.MoveAndResizeControlWindow2",
                    "Children": [
                    ]
                  }
                ]
              },
              {
                "Title": "TreeView that allows multiple selection(多选TreeView)",
                "DllName": "WpfDemo.exe",
                "ClassName": "WpfDemo.MultiSelectors.MultiSelectorWindow",
                "Children": [
                ]
              },
              {
                "Title": "Customized UserControl ProcessBar(自定义进度条)",
                "DllName": "WpfDemo.exe",
                "ClassName": "WpfDemo.ProcessBars.ProcessBarWithTextWindow",
                "Children": [
                ]
              },
              {
                "Title": "Customized Border(自定义Border)",
                "DllName": "WpfDemo.exe",
                "ClassName": "WpfDemo.DependencyProperties.TestCustomTextBlock",
                "Children": [
                ]
              },
              {
                "Title": "Customized Button(自定义按钮)",
                "DllName": "",
                "ClassName": "",
                "Children": [
                  {
                    "Title": "Customized Button1",
                    "DllName": "WpfDemo.exe",
                    "ClassName": "WpfDemo.CustomButton.TestCustomButtonWindow",
                    "Children": [
                    ]
                  },
                  {
                    "Title": "Customized Button2",
                    "DllName": "WpfDemo.exe",
                    "ClassName": "WpfDemo.CustomerWindow.ButtonShowToolTip",
                    "Children": [
                    ]
                  }
                ]
              },
              {
                "Title": "Single choice TreeView(单选TreeView)",
                "DllName": "",
                "ClassName": "",
                "Children": [
                  {
                    "Title": "Custom UserControl SingleSelector Front-end Generation(SingleSelector前端生成)",
                    "DllName": "WpfDemo.exe",
                    "ClassName": "WpfDemo.SingleSelectors.SingleSelectorWindow",
                    "Children": [
                    ]
                  },
                  {
                    "Title": "Custom UserControl SingleSelector Back-end Generation(SingleSelector后端生成)",
                    "DllName": "WpfDemo.exe",
                    "ClassName": "WpfDemo.SingleSelectors.SingleSelectorWindow2",
                    "Children": [
                    ]
                  },
                  {
                    "Title": "Custom UserControl SingleSelector2 Front-end Generation(SingleSelector2后端生成)",
                    "DllName": "WpfDemo.exe",
                    "ClassName": "WpfDemo.SingleSelectors.SingleSelectorWindow3",
                    "Children": [
                    ]
                  }
                ]
              }
            ]
          },
          {
            "Title": "CheckBox",
            "DllName": "",
            "ClassName": "",
            "Children": [

              {
                "Title": "Basic use of CheckBox(CheckBox基础使用)",
                "DllName": "WpfDemo.exe",
                "ClassName": "WpfDemo.CheckBox.CheckBoxDemo",
                "Children": [
                ]
              },
              {
                "Title": "CheckBox and DataGrid(CheckBox和DataGrid)",
                "DllName": "WpfDemo.exe",
                "ClassName": "WpfDemo.CheckBox.SelectAllAndCancleCheckBoxWindow",
                "Children": [
                ]
              }
            ]
          },
          {
            "Title": "Tab with close button(带关闭按钮的Tab)",
            "DllName": "WpfDemo.exe",
            "ClassName": "WpfDemo.ClosableTabs.ClosableTabDemo",
            "Children": [
            ]
          },
          {
            "Title": "Generate menu(菜单栏)",
            "DllName": "WpfDemo.exe",
            "ClassName": "WpfDemo.ContextMenus.CreateContextMenuWindow",
            "Children": [
            ]
          },
          {
            "Title": "Border",
            "DllName": "",
            "ClassName": "",
            "Children": [
              {
                "Title": "The magical Border response problem(神奇的Border响应问题)",
                "DllName": "WpfDemo.exe",
                "ClassName": "WpfDemo.Borders.BorderTestWindow",
                "Children": [
                ]
              }
            ]
          },
          {
            "Title": "ComboBox",
            "DllName": "",
            "ClassName": "",
            "Children": [
              {
                "Title": "ComboBox does not set SelectedValuePath(ComboBox不设置SelectedValuePath)",
                "DllName": "WpfDemo.exe",
                "ClassName": "WpfDemo.UseComboBox.UseComboBoxDemo",
                "Children": [
                ]
              },
              {
                "Title": "ComboBox set SelectedValuePath(ComboBox设置SelectedValuePath)",
                "DllName": "WpfDemo.exe",
                "ClassName": "WpfDemo.UseComboBox.UseComboBoxDemo2",
                "Children": [
                ]
              }
            ]
          },
          {
            "Title": "Basic use of Expander(Expander基本使用)",
            "DllName": "WpfDemo.exe",
            "ClassName": "WpfDemo.Expander.ExpanderDemo",
            "Children": [
            ]
          },
          {
            "Title": "Basic use of ItemsControl(ItemsControl基本使用)",
            "DllName": "WpfDemo.exe",
            "ClassName": "WpfDemo.ItemsControls.ItemsControlDemo",
            "Children": [
            ]
          },
          {
            "Title": "DataGrid",
            "DllName": "",
            "ClassName": "",
            "Children": [
              {
                "Title": "DataGrid loads data asynchronously(DataGrid 异步加载数据)",
                "DllName": "WpfDemo.exe",
                "ClassName": "WpfDemo.LoadingDataAsync.LoadingDataAsyncWindow",
                "Children": [
                ]
              }
            ]
          },
          {
            "Title": "Navigation page(导航页)",
            "DllName": "WpfDemo.exe",
            "ClassName": "WpfDemo.Navigation.NavigationStartPage",
            "Children": [

            ]
          },
          {
            "Title": "Multiple UserControls switching(多用户控件切换)",
            "DllName": "WpfDemo.exe",
            "ClassName": "WpfDemo.NavigationPages.DemoWindow",
            "Children": [
            ]
          },
          {
            "Title": "Borderless Window(无边框窗口)",
            "DllName": "WpfDemo.exe",
            "ClassName": "WpfDemo.NoneBorder.NoneBorderStartPage",
            "Children": [
            ]
          },
          {
            "Title": "Basic use of RadioButton(RadioButton基本使用)",
            "DllName": "WpfDemo.exe",
            "ClassName": "WpfDemo.RadioButton.RadioButtonDemo",
            "Children": [
            ]
          },
          {
            "Title": "Dialog(对话框)",
            "DllName": "WpfDemo.exe",
            "ClassName": "WpfDemo.StartWindowAndDialog.StartWindow",
            "Children": [
            ]
          },
          {
            "Title": "TabIndex(TabIndex属性的使用)",
            "DllName": "WpfDemo.exe",
            "ClassName": "WpfDemo.TabSetting.TabSettingDemo",
            "Children": [
            ]
          },
          {
            "Title": "Tag(Tag使用)",
            "DllName": "WpfDemo.exe",
            "ClassName": "WpfDemo.Tag.TagDemo",
            "Children": [
            ]
          },
          {
            "Title": "TextBlock Run Property(TextBlock Run属性使用)",
            "DllName": "WpfDemo.exe",
            "ClassName": "WpfDemo.TextBlockRun.TextBlockRunDemo",
            "Children": [
            ]
          },
          {
            "Title": "ScrollViewer",
            "DllName": "WpfDemo.exe",
            "ClassName": "WpfDemo.ScrollViewers.MoveScrollViewerByCode",
            "Children": [
            ]
          }
        ]
      },
      {
        "Title": "Binding(绑定)",
        "DllName": "",
        "ClassName": "",
        "Children": [
          {
            "Title": "Simple Binding(简单绑定)",
            "DllName": "WpfDemo.exe",
            "ClassName": "WpfDemo.Bind.BindDemoForINotifyPropertyChanged",
            "Children": [
            ]
          },
          {
            "Title": "Binding in WPF Controls(控件绑定)",
            "DllName": "WpfDemo.exe",
            "ClassName": "WpfDemo.Bind.BindDemoForView",
            "Children": [
            ]
          },
          {
            "Title": "DataGrid Binding in Code(DataGrid后台绑定)",
            "DllName": "WpfDemo.exe",
            "ClassName": "WpfDemo.Bind.DataGridBackgroundBind",
            "Children": [
            ]
          },
          {
            "Title": "Complex Binding of DataGrid(DataGrid前端复杂绑定)",
            "DllName": "WpfDemo.exe",
            "ClassName": "WpfDemo.Bind.DataGridBindMultiData",
            "Children": [
            ]
          },
          {
            "Title": "DataGrid DataContext And ItemSource",
            "DllName": "WpfDemo.exe",
            "ClassName": "WpfDemo.DataContextAndItemSource.DataContextAndItemSource",
            "Children": [
            ]
          },
          {
            "Title": "MultiBinding",
            "DllName": "",
            "ClassName": "",
            "Children": [
              {
                "Title": "MultiBinding",
                "DllName": "WpfDemo.exe",
                "ClassName": "WpfDemo.MultiBinding.MultiBindingDemo",
                "Children": [

                ]
              },
              {
                "Title": "MultiBinding with Converter",
                "DllName": "WpfDemo.exe",
                "ClassName": "WpfDemo.MultiBinding.MultiBinding2.MultiBinding2",
                "Children": [

                ]
              }
            ]
          },
          {
            "Title": "Update Datasource(修改数据源)",
            "DllName": "WpfDemo.exe",
            "ClassName": "WpfDemo.PropertyChanged.ChangeStudentInfo",
            "Children": [
            ]
          },
          {
            "Title": "Binding of ListView(ListView绑定)",
            "DllName": "WpfDemo.exe",
            "ClassName": "WpfDemo.Template.DataTemplate.DataTemplateDemo2",
            "Children": [
            ]
          }
        ]
      },
      {
        "Title": "Resources(使用资源)",
        "DllName": "",
        "ClassName": "",
        "Children": [
          {
            "Title": "Array Resources(资源数组)",
            "DllName": "WpfDemo.exe",
            "ClassName": "WpfDemo.ArrayExtension.ArrayExtensionDemo",
            "Children": [
            ]
          },
          {
            "Title": "StaticResource in code(后台静态资源)",
            "DllName": "WpfDemo.exe",
            "ClassName": "WpfDemo.GetStaticFromBackgroundCode.GetStaticFromBackgroundCode",
            "Children": [
            ]
          },
          {
            "Title": "Background Image(设置图片背景)",
            "DllName": "WpfDemo.exe",
            "ClassName": "WpfDemo.WindowIconAndBackground.WindowIconAndBackgroundStartPage",
            "Children": [
            ]
          }
        ]
      },
      {
        "Title": "Style(样式)",
        "DllName": "",
        "ClassName": "",
        "Children": [
          {
            "Title": "Style1(在文件中设置样式1)",
            "DllName": "WpfDemo.exe",
            "ClassName": "WpfDemo.Style.StyleDemo",
            "Children": [
            ]
          },
          {
            "Title": "Use StaticResource to Style(使用静态资源设置样式)",
            "DllName": "WpfDemo.exe",
            "ClassName": "WpfDemo.Style.StyleDemo2",
            "Children": [
            ]
          },
          {
            "Title": "Use StaticResource to Style2(使用静态资源设置样式2)",
            "DllName": "WpfDemo.exe",
            "ClassName": "WpfDemo.Style.StyleInheritDemo",
            "Children": [
            ]
          },
          {
            "Title": "Style Inheritance(样式继承)",
            "DllName": "WpfDemo.exe",
            "ClassName": "WpfDemo.Style.StyleInheritDemo2",
            "Children": [
            ]
          },
          {
            "Title": "Reference Style File(引用样式文件)",
            "DllName": "WpfDemo.exe",
            "ClassName": "WpfDemo.Style.UseResourceDictionaryDemo",
            "Children": [
            ]
          }
        ]
      },
      {
        "Title": "Template",
        "DllName": "",
        "ClassName": "",
        "Children": [
          {
            "Title": "ControlTemplate",
            "DllName": "",
            "ClassName": "",
            "Children": [
              {
                "Title": "ControlTemplate1",
                "DllName": "WpfDemo.exe",
                "ClassName": "WpfDemo.Template.ControlTemplate.ControlTemplateDemo",
                "Children": [
                ]
              },
              {
                "Title": "ControlTemplate2",
                "DllName": "WpfDemo.exe",
                "ClassName": "WpfDemo.Template.ControlTemplate.ControlTemplateDemo2",
                "Children": [
                ]
              },
              {
                "Title": "ControlTemplate3",
                "DllName": "WpfDemo.exe",
                "ClassName": "WpfDemo.Template.ControlTemplate.ControlTemplateDemo3",
                "Children": [
                ]
              },
              {
                "Title": "VisualStateManager",
                "DllName": "WpfDemo.exe",
                "ClassName": "WpfDemo.VisualStateManager.VisualStateManagerDemo",
                "Children": [
                ]
              }
            ]
          },
          {
            "Title": "DataTemplate",
            "DllName": "",
            "ClassName": "",
            "Children": [
              {
                "Title": "DataTemplate in Code(DataTemplate后端)",
                "DllName": "WpfDemo.exe",
                "ClassName": "WpfDemo.Template.DataTemplate.DataTemplateByCodeDemoWindow",
                "Children": [
                ]
              },
              {
                "Title": "DataTemplate in Xml(DataTemplate前端)",
                "DllName": "WpfDemo.exe",
                "ClassName": "WpfDemo.Template.DataTemplate.DataTemplateDemo",
                "Children": [
                ]
              }
            ]
          },
          {
            "Title": "ItemsPanelTemplate & DataTemplate",
            "DllName": "WpfDemo.exe",
            "ClassName": "WpfDemo.Template.ItemsPanelTemplate.ItemsPanelTemplateDemo",
            "Children": [

            ]
          },
          {
            "Title": "Use Template in Style(在Style中使用Template)",
            "DllName": "WpfDemo.exe",
            "ClassName": "WpfDemo.StyleUseTemplate.StyleUseTemplateDemo",
            "Children": [

            ]
          }
        ]
      },
      {
        "Title": "Trigger(触发器)",
        "DllName": "",
        "ClassName": "",
        "Children": [
          {
            "Title": "Trigger",
            "DllName": "WpfDemo.exe",
            "ClassName": "WpfDemo.Trigger.TriggerDemo",
            "Children": [
            ]
          },
          {
            "Title": "EventTrigger",
            "DllName": "WpfDemo.exe",
            "ClassName": "WpfDemo.Trigger.EventTriggerDemo",
            "Children": [
            ]
          },
          {
            "Title": "MultiTrigger",
            "DllName": "WpfDemo.exe",
            "ClassName": "WpfDemo.Trigger.MultiTriggerDemo",
            "Children": [
            ]
          },
          {
            "Title": "DataTrigger",
            "DllName": "WpfDemo.exe",
            "ClassName": "WpfDemo.Trigger.DataTriggerDemo",
            "Children": [
            ]
          },
          {
            "Title": "DataTrigger2",
            "DllName": "WpfDemo.exe",
            "ClassName": "WpfDemo.Trigger.DataTriggerDemo2",
            "Children": [
            ]
          }
        ]
      },
      {
        "Title": "Animation(动画)",
        "DllName": "",
        "ClassName": "",
        "Children": [
          {
            "Title": "Animation in Code(后端生成动画)",
            "DllName": "WpfDemo.exe",
            "ClassName": "WpfDemo.Animations.RectangleAnimationWindow",
            "Children": [
            ]
          },
          {
            "Title": "Animation in Xml(前端生成动画)",
            "DllName": "WpfDemo.exe",
            "ClassName": "WpfDemo.Animations.RectangleAnimationWindow2",
            "Children": [
            ]
          },
          {
            "Title": "Loading Mark(加载动画)",
            "DllName": "WpfDemo.exe",
            "ClassName": "WpfDemo.LoadingMarks.Demo",
            "Children": [
            ]
          }
        ]
      },
      {
        "Title": "Logical and Visual Trees(逻辑树和视觉树)",
        "DllName": "WpfDemo.exe",
        "ClassName": "WpfDemo.LogicalTreeAndVisualTree.LogicalTreeAndVisualTreeWindow",
        "Children": [
        ]
      },
      {
        "Title": "Layout(布局)",
        "DllName": "WpfDemo.exe",
        "ClassName": "WpfDemo.Modules.ModuleMainWindow",
        "Children": [
        ]
      },
      {
        "Title": "Margin and Padding(Margin 和 Padding)",
        "DllName": "WpfDemo.exe",
        "ClassName": "WpfDemo.MarginAndPadding.MarginAndPaddingDemo",
        "Children": [
        ]
      },
      {
        "Title": "Command",
        "DllName": "",
        "ClassName": "",
        "Children": [
          {
            "Title": "Command1",
            "DllName": "WpfDemo.exe",
            "ClassName": "WpfDemo.Command.CommandDemoWithBindParameters",
            "Children": [
            ]
          },
          {
            "Title": "Command1",
            "DllName": "WpfDemo.exe",
            "ClassName": "WpfDemo.Command.CommandDemoWithParameters",
            "Children": [
            ]
          }
        ]
      },
      {
        "Title": "Converter",
        "DllName": "",
        "ClassName": "",
        "Children": [
          {
            "Title": "Basic use of Converter(Converter基本使用)",
            "DllName": "WpfDemo.exe",
            "ClassName": "WpfDemo.Converters.ForForm.FormWindow",
            "Children": [
            ]
          },
          {
            "Title": "Converter and DataGrid(Converter 和 DataGrid)",
            "DllName": "WpfDemo.exe",
            "ClassName": "WpfDemo.Converters.DataGridWindow",
            "Children": [
            ]
          },
          {
            "Title": "ColorConvert",
            "DllName": "WpfDemo.exe",
            "ClassName": "WpfDemo.Converts.ConvertDemo",
            "Children": [
            ]
          }
        ]
      },
      {
        "Title": "Other(其他)",
        "DllName": "",
        "ClassName": "",
        "Children": [
          {
            "Title": "Use Dispatcher to modify the UI(使用Dispatcher修改UI)",
            "DllName": "WpfDemo.exe",
            "ClassName": "WpfDemo.ChangeUI.ChangeUIDemo",
            "Children": [
            ]
          },
          {
            "Title": "FTP",
            "DllName": "WpfDemo.exe",
            "ClassName": "WpfDemo.FTP.FTPWindow",
            "Children": [
            ]
          },
          {
            "Title": "Historical data processing (horizontal sub-database sub-table) 历史数据处理(水平分库分表)",
            "DllName": "WpfDemo.exe",
            "ClassName": "WpfDemo.HistoricalDataManage.HistoricalDataManageWithTimeWindow",
            "Children": [
            ]
          },
          {
            "Title": "Open Files(打开文件)",
            "DllName": "WpfDemo.exe",
            "ClassName": "WpfDemo.OpenFiles.OpenTxtFileWindow",
            "Children": [
            ]
          },
          {
            "Title": "Task Management(任务管理)",
            "DllName": "",
            "ClassName": "",
            "Children": [
              {
                "Title": "Task Management By Task(任务管理-Task)",
                "DllName": "WpfDemo.exe",
                "ClassName": "WpfDemo.PauseAndResumeTask.PauseAndResumeTaskWindow",
                "Children": [
                ]
              },
              {
                "Title": "Task Management By Thread(任务管理-Thread)",
                "DllName": "WpfDemo.exe",
                "ClassName": "WpfDemo.PauseAndResumeThread.PauseAndResumeThreadWindow",
                "Children": [
                ]
              }
            ]
          },
          {
            "Title": "Print Picture(打印图片)",
            "DllName": "",
            "ClassName": "",
            "Children": [
              {
                "Title": "Print Picture1(打印图片1)",
                "DllName": "WpfDemo.exe",
                "ClassName": "WpfDemo.PrintImage.PrintImageWindow",
                "Children": [
                ]
              },
              {
                "Title": "Print Picture2 - Provide printing options(打印图片2 提供打印选项)",
                "DllName": "WpfDemo.exe",
                "ClassName": "WpfDemo.PrintImage.PrintImageWithPageSettingWindow",
                "Children": [
                ]
              },
              {
                "Title": "Print Picture3 - Provide printing options and zoom function(打印图片3 提供打印选项+缩放功能)",
                "DllName": "WpfDemo.exe",
                "ClassName": "WpfDemo.PrintImage.PrintImageWithPageSettingWindow2",
                "Children": [
                ]
              }
            ]
          },
          {
            "Title": "Print Form(打开表单)",
            "DllName": "WpfDemo.exe",
            "ClassName": "WpfDemo.PrintTable.PrintTableStartPage",
            "Children": [
            ]
          },
          {
            "Title": "ShowInTaskbar=false Window(ShowInTaskbar=false的窗口)",
            "DllName": "WpfDemo.exe",
            "ClassName": "WpfDemo.NotShowInTaskbarWindows.NotShowInTaskbarTab",
            "Children": [
            ]
          }
        ]
      }
    ]
  }
]